LICENSE.md
MANIFEST.in
README.md
setup.py
admin_modernize/__init__.py
admin_modernize/admin.py
admin_modernize/apps.py
admin_modernize/forms.py
admin_modernize/models.py
admin_modernize/tests.py
admin_modernize/urls.py
admin_modernize/utils.py
admin_modernize/views.py
admin_modernize/static/.gitkeep
admin_modernize/static/assets/css/forms.css
admin_modernize/static/assets/css/style-preset.css
admin_modernize/static/assets/css/styles.css
admin_modernize/static/assets/css/styles.min.css
admin_modernize/static/assets/css/widgets.css
admin_modernize/static/assets/css/icons/tabler-icons/tabler-icons.css
admin_modernize/static/assets/css/icons/tabler-icons/fonts/tabler-icons.eot
admin_modernize/static/assets/css/icons/tabler-icons/fonts/tabler-icons.svg
admin_modernize/static/assets/css/icons/tabler-icons/fonts/tabler-icons.ttf
admin_modernize/static/assets/css/icons/tabler-icons/fonts/tabler-icons.woff
admin_modernize/static/assets/css/icons/tabler-icons/fonts/tabler-icons.woff2
admin_modernize/static/assets/css/plugins/animate.min.css
admin_modernize/static/assets/css/plugins/bootstrap.min.css
admin_modernize/static/assets/images/backgrounds/rocket.png
admin_modernize/static/assets/images/logos/dark-logo.svg
admin_modernize/static/assets/images/logos/favicon.png
admin_modernize/static/assets/images/products/s1.jpg
admin_modernize/static/assets/images/products/s11.jpg
admin_modernize/static/assets/images/products/s4.jpg
admin_modernize/static/assets/images/products/s5.jpg
admin_modernize/static/assets/images/products/s7.jpg
admin_modernize/static/assets/images/profile/user-1.jpg
admin_modernize/static/assets/js/app.min.js
admin_modernize/static/assets/js/dashboard.js
admin_modernize/static/assets/js/sidebarmenu.js
admin_modernize/static/assets/libs/apexcharts/LICENSE
admin_modernize/static/assets/libs/apexcharts/README.md
admin_modernize/static/assets/libs/apexcharts/package.json
admin_modernize/static/assets/libs/apexcharts/dist/apexcharts.amd.js
django_admin_modernize.egg-info/PKG-INFO
django_admin_modernize.egg-info/SOURCES.txt
django_admin_modernize.egg-info/dependency_links.txt
django_admin_modernize.egg-info/not-zip-safe
django_admin_modernize.egg-info/top_level.txt
